src/__init__.py
src/main.py
python_fast_api_kube-0.0.0.dist-info/LICENSE
python_fast_api_kube-0.0.0.dist-info/METADATA
python_fast_api_kube-0.0.0.dist-info/WHEEL
python_fast_api_kube-0.0.0.dist-info/top_level.txt
python_fast_api_kube-0.0.0.dist-info/RECORD
