Metadata-Version: 2.1
Name: python-fast-api-kube
Version: 0.0.0
Summary: python-fast-api-kube
Home-page: https://github.com/maher-naija-pro/fast-api-kube
Author: maher naija
Author-email: maher.naija@gmail.Com
License: MIT
License-File: LICENSE
